<annotation>
    <folder>OurDataset</folder>
    <filename>007-2112-100.jpg</filename>
    <size>
        <width>2592</width>
        <height>1728</height>
        <depth>3</depth>
    </size>
    <object>
        <name>ma</name>
        <pose>Unspecified</pose>
        <truncated>0</truncated>
        <difficult>0</difficult>
        <bndbox>
            <xmin>705</xmin>
            <ymin>713</ymin>
            <xmax>709</xmax>
            <ymax>719</ymax>
        </bndbox>
    </object>
    <object>
        <name>ma</name>
        <pose>Unspecified</pose>
        <truncated>0</truncated>
        <difficult>0</difficult>
        <bndbox>
            <xmin>1089</xmin>
            <ymin>889</ymin>
            <xmax>1097</xmax>
            <ymax>895</ymax>
        </bndbox>
    </object>
    <object>
        <name>ma</name>
        <pose>Unspecified</pose>
        <truncated>0</truncated>
        <difficult>0</difficult>
        <bndbox>
            <xmin>1177</xmin>
            <ymin>305</ymin>
            <xmax>1185</xmax>
            <ymax>313</ymax>
        </bndbox>
    </object>
    <object>
        <name>ma</name>
        <pose>Unspecified</pose>
        <truncated>0</truncated>
        <difficult>0</difficult>
        <bndbox>
            <xmin>1261</xmin>
            <ymin>929</ymin>
            <xmax>1271</xmax>
            <ymax>937</ymax>
        </bndbox>
    </object>
    <object>
        <name>he</name>
        <pose>Unspecified</pose>
        <truncated>0</truncated>
        <difficult>0</difficult>
        <bndbox>
            <xmin>853</xmin>
            <ymin>1267</ymin>
            <xmax>869</xmax>
            <ymax>1293</ymax>
        </bndbox>
    </object>
    <object>
        <name>he</name>
        <pose>Unspecified</pose>
        <truncated>0</truncated>
        <difficult>0</difficult>
        <bndbox>
            <xmin>873</xmin>
            <ymin>1285</ymin>
            <xmax>875</xmax>
            <ymax>1289</ymax>
        </bndbox>
    </object>
    <object>
        <name>ma</name>
        <pose>Unspecified</pose>
        <truncated>0</truncated>
        <difficult>0</difficult>
        <bndbox>
            <xmin>705</xmin>
            <ymin>713</ymin>
            <xmax>709</xmax>
            <ymax>719</ymax>
        </bndbox>
    </object>
    <object>
        <name>ma</name>
        <pose>Unspecified</pose>
        <truncated>0</truncated>
        <difficult>0</difficult>
        <bndbox>
            <xmin>1089</xmin>
            <ymin>889</ymin>
            <xmax>1097</xmax>
            <ymax>895</ymax>
        </bndbox>
    </object>
    <object>
        <name>ma</name>
        <pose>Unspecified</pose>
        <truncated>0</truncated>
        <difficult>0</difficult>
        <bndbox>
            <xmin>1177</xmin>
            <ymin>305</ymin>
            <xmax>1185</xmax>
            <ymax>313</ymax>
        </bndbox>
    </object>
    <object>
        <name>ma</name>
        <pose>Unspecified</pose>
        <truncated>0</truncated>
        <difficult>0</difficult>
        <bndbox>
            <xmin>1261</xmin>
            <ymin>929</ymin>
            <xmax>1271</xmax>
            <ymax>937</ymax>
        </bndbox>
    </object>
    <object>
        <name>he</name>
        <pose>Unspecified</pose>
        <truncated>0</truncated>
        <difficult>0</difficult>
        <bndbox>
            <xmin>853</xmin>
            <ymin>1267</ymin>
            <xmax>869</xmax>
            <ymax>1293</ymax>
        </bndbox>
    </object>
    <object>
        <name>he</name>
        <pose>Unspecified</pose>
        <truncated>0</truncated>
        <difficult>0</difficult>
        <bndbox>
            <xmin>873</xmin>
            <ymin>1285</ymin>
            <xmax>875</xmax>
            <ymax>1289</ymax>
        </bndbox>
    </object>
</annotation>