<annotation>
    <folder>OurDataset</folder>
    <filename>007-2300-100.jpg</filename>
    <size>
        <width>2736</width>
        <height>1824</height>
        <depth>3</depth>
    </size>
    <object>
        <name>ma</name>
        <pose>Unspecified</pose>
        <truncated>0</truncated>
        <difficult>0</difficult>
        <bndbox>
            <xmin>741</xmin>
            <ymin>851</ymin>
            <xmax>751</xmax>
            <ymax>871</ymax>
        </bndbox>
    </object>
    <object>
        <name>ma</name>
        <pose>Unspecified</pose>
        <truncated>0</truncated>
        <difficult>0</difficult>
        <bndbox>
            <xmin>953</xmin>
            <ymin>743</ymin>
            <xmax>957</xmax>
            <ymax>747</ymax>
        </bndbox>
    </object>
    <object>
        <name>ma</name>
        <pose>Unspecified</pose>
        <truncated>0</truncated>
        <difficult>0</difficult>
        <bndbox>
            <xmin>953</xmin>
            <ymin>761</ymin>
            <xmax>957</xmax>
            <ymax>767</ymax>
        </bndbox>
    </object>
    <object>
        <name>ma</name>
        <pose>Unspecified</pose>
        <truncated>0</truncated>
        <difficult>0</difficult>
        <bndbox>
            <xmin>971</xmin>
            <ymin>731</ymin>
            <xmax>979</xmax>
            <ymax>741</ymax>
        </bndbox>
    </object>
    <object>
        <name>ma</name>
        <pose>Unspecified</pose>
        <truncated>0</truncated>
        <difficult>0</difficult>
        <bndbox>
            <xmin>1115</xmin>
            <ymin>689</ymin>
            <xmax>1119</xmax>
            <ymax>693</ymax>
        </bndbox>
    </object>
    <object>
        <name>ma</name>
        <pose>Unspecified</pose>
        <truncated>0</truncated>
        <difficult>0</difficult>
        <bndbox>
            <xmin>1365</xmin>
            <ymin>1229</ymin>
            <xmax>1375</xmax>
            <ymax>1235</ymax>
        </bndbox>
    </object>
    <object>
        <name>ma</name>
        <pose>Unspecified</pose>
        <truncated>0</truncated>
        <difficult>0</difficult>
        <bndbox>
            <xmin>1669</xmin>
            <ymin>391</ymin>
            <xmax>1675</xmax>
            <ymax>397</ymax>
        </bndbox>
    </object>
    <object>
        <name>ma</name>
        <pose>Unspecified</pose>
        <truncated>0</truncated>
        <difficult>0</difficult>
        <bndbox>
            <xmin>1949</xmin>
            <ymin>1385</ymin>
            <xmax>1957</xmax>
            <ymax>1393</ymax>
        </bndbox>
    </object>
    <object>
        <name>ma</name>
        <pose>Unspecified</pose>
        <truncated>0</truncated>
        <difficult>0</difficult>
        <bndbox>
            <xmin>1971</xmin>
            <ymin>1207</ymin>
            <xmax>1977</xmax>
            <ymax>1219</ymax>
        </bndbox>
    </object>
    <object>
        <name>ma</name>
        <pose>Unspecified</pose>
        <truncated>0</truncated>
        <difficult>0</difficult>
        <bndbox>
            <xmin>1979</xmin>
            <ymin>1379</ymin>
            <xmax>1991</xmax>
            <ymax>1389</ymax>
        </bndbox>
    </object>
    <object>
        <name>ma</name>
        <pose>Unspecified</pose>
        <truncated>0</truncated>
        <difficult>0</difficult>
        <bndbox>
            <xmin>741</xmin>
            <ymin>851</ymin>
            <xmax>751</xmax>
            <ymax>871</ymax>
        </bndbox>
    </object>
    <object>
        <name>ma</name>
        <pose>Unspecified</pose>
        <truncated>0</truncated>
        <difficult>0</difficult>
        <bndbox>
            <xmin>953</xmin>
            <ymin>743</ymin>
            <xmax>957</xmax>
            <ymax>747</ymax>
        </bndbox>
    </object>
    <object>
        <name>ma</name>
        <pose>Unspecified</pose>
        <truncated>0</truncated>
        <difficult>0</difficult>
        <bndbox>
            <xmin>953</xmin>
            <ymin>761</ymin>
            <xmax>957</xmax>
            <ymax>767</ymax>
        </bndbox>
    </object>
    <object>
        <name>ma</name>
        <pose>Unspecified</pose>
        <truncated>0</truncated>
        <difficult>0</difficult>
        <bndbox>
            <xmin>971</xmin>
            <ymin>731</ymin>
            <xmax>979</xmax>
            <ymax>741</ymax>
        </bndbox>
    </object>
    <object>
        <name>ma</name>
        <pose>Unspecified</pose>
        <truncated>0</truncated>
        <difficult>0</difficult>
        <bndbox>
            <xmin>1115</xmin>
            <ymin>689</ymin>
            <xmax>1119</xmax>
            <ymax>693</ymax>
        </bndbox>
    </object>
    <object>
        <name>ma</name>
        <pose>Unspecified</pose>
        <truncated>0</truncated>
        <difficult>0</difficult>
        <bndbox>
            <xmin>1365</xmin>
            <ymin>1229</ymin>
            <xmax>1375</xmax>
            <ymax>1235</ymax>
        </bndbox>
    </object>
    <object>
        <name>ma</name>
        <pose>Unspecified</pose>
        <truncated>0</truncated>
        <difficult>0</difficult>
        <bndbox>
            <xmin>1669</xmin>
            <ymin>391</ymin>
            <xmax>1675</xmax>
            <ymax>397</ymax>
        </bndbox>
    </object>
    <object>
        <name>ma</name>
        <pose>Unspecified</pose>
        <truncated>0</truncated>
        <difficult>0</difficult>
        <bndbox>
            <xmin>1949</xmin>
            <ymin>1385</ymin>
            <xmax>1957</xmax>
            <ymax>1393</ymax>
        </bndbox>
    </object>
    <object>
        <name>ma</name>
        <pose>Unspecified</pose>
        <truncated>0</truncated>
        <difficult>0</difficult>
        <bndbox>
            <xmin>1971</xmin>
            <ymin>1207</ymin>
            <xmax>1977</xmax>
            <ymax>1219</ymax>
        </bndbox>
    </object>
    <object>
        <name>ma</name>
        <pose>Unspecified</pose>
        <truncated>0</truncated>
        <difficult>0</difficult>
        <bndbox>
            <xmin>1979</xmin>
            <ymin>1379</ymin>
            <xmax>1991</xmax>
            <ymax>1389</ymax>
        </bndbox>
    </object>
</annotation>